Dependency.py
POM.py
POMREPOS.py
ScanDir.py
pyXhPomMgmt.py
pyXhPomMgmt-0.0.2.dist-info/METADATA
pyXhPomMgmt-0.0.2.dist-info/WHEEL
pyXhPomMgmt-0.0.2.dist-info/entry_points.txt
pyXhPomMgmt-0.0.2.dist-info/top_level.txt
pyXhPomMgmt-0.0.2.dist-info/RECORD
