Metadata-Version: 2.1
Name: pyXhPomMgmt
Version: 0.0.2
Summary: python maven pom info extractor
Home-page: https://github.com/xh-dev-py/pyXhPomMgmt
Author: xethhung
Author-email: pypi@xethh.dev
License: UNKNOWN
Platform: UNKNOWN
Provides-Extra: dev
Requires-Dist: pytest (>=3.7) ; extra == 'dev'
